aws_solutions_constructs/aws_dynamodb_stream_lambda_elasticsearch_kibana/__init__.py
aws_solutions_constructs/aws_dynamodb_stream_lambda_elasticsearch_kibana/py.typed
aws_solutions_constructs/aws_dynamodb_stream_lambda_elasticsearch_kibana/_jsii/__init__.py
aws_solutions_constructs/aws_dynamodb_stream_lambda_elasticsearch_kibana/_jsii/aws-dynamodb-stream-lambda-elasticsearch-kibana@1.181.1.jsii.tgz
aws_solutions_constructs.aws_dynamodb_stream_lambda_elasticsearch_kibana-1.181.1.dist-info/LICENSE
aws_solutions_constructs.aws_dynamodb_stream_lambda_elasticsearch_kibana-1.181.1.dist-info/METADATA
aws_solutions_constructs.aws_dynamodb_stream_lambda_elasticsearch_kibana-1.181.1.dist-info/WHEEL
aws_solutions_constructs.aws_dynamodb_stream_lambda_elasticsearch_kibana-1.181.1.dist-info/top_level.txt
aws_solutions_constructs.aws_dynamodb_stream_lambda_elasticsearch_kibana-1.181.1.dist-info/RECORD
