Metadata-Version: 2.1
Name: aws-solutions-constructs.aws-dynamodb-stream-lambda-elasticsearch-kibana
Version: 1.181.1
Summary: CDK Constructs for Amazon Dynamodb stream to AWS Lambda to AWS Elasticsearch with Kibana integration
Home-page: https://github.com/awslabs/aws-solutions-constructs.git
Author: Amazon Web Services
License: Apache-2.0
Project-URL: Source, https://github.com/awslabs/aws-solutions-constructs.git
Platform: UNKNOWN
Classifier: Intended Audience :: Developers
Classifier: Operating System :: OS Independent
Classifier: Programming Language :: JavaScript
Classifier: Programming Language :: Python :: 3 :: Only
Classifier: Programming Language :: Python :: 3.7
Classifier: Programming Language :: Python :: 3.8
Classifier: Programming Language :: Python :: 3.9
Classifier: Programming Language :: Python :: 3.10
Classifier: Typing :: Typed
Classifier: License :: OSI Approved
Requires-Python: ~=3.7
License-File: LICENSE
Requires-Dist: aws-cdk.aws-cloudwatch (==1.181.1)
Requires-Dist: aws-cdk.aws-cognito (==1.181.1)
Requires-Dist: aws-cdk.aws-dynamodb (==1.181.1)
Requires-Dist: aws-cdk.aws-elasticsearch (==1.181.1)
Requires-Dist: aws-cdk.aws-iam (==1.181.1)
Requires-Dist: aws-cdk.aws-lambda-event-sources (==1.181.1)
Requires-Dist: aws-cdk.aws-lambda (==1.181.1)
Requires-Dist: aws-cdk.aws-sqs (==1.181.1)
Requires-Dist: aws-cdk.core (==1.181.1)
Requires-Dist: aws-solutions-constructs.aws-dynamodbstreams-lambda-elasticsearch-kibana (==1.181.1)
Requires-Dist: aws-solutions-constructs.core (==1.181.1)
Requires-Dist: constructs (<4.0.0,>=3.2.0)
Requires-Dist: jsii (<2.0.0,>=1.71.0)
Requires-Dist: publication (>=0.0.3)
Requires-Dist: typeguard (~=2.13.3)
